libname/__init__.py
libname/run.py
jikuxd-0.1.0.dist-info/METADATA
jikuxd-0.1.0.dist-info/WHEEL
jikuxd-0.1.0.dist-info/top_level.txt
jikuxd-0.1.0.dist-info/RECORD
