Metadata-Version: 2.1
Name: jikuxd
Version: 0.1.0
Summary: This is my personal tool
Home-page: https://github.com/phinerx
Author: Personal Tool
Author-email: phinerx749@gmail.com
Classifier: Programming Language :: Python :: 3
Classifier: License :: OSI Approved :: MIT License
Classifier: Operating System :: OS Independent
Requires-Python: >=3.6
